Songs/__init__.py
Songs/shazam.py
Weather/__init__.py
Weather/weatherapi.py
Weather/weatherbit.py
dobrepraktyki-1.0.dist-info/METADATA
dobrepraktyki-1.0.dist-info/WHEEL
dobrepraktyki-1.0.dist-info/top_level.txt
dobrepraktyki-1.0.dist-info/RECORD
