Metadata-Version: 2.1
Name: dobrepraktyki
Version: 1.0
Summary: UNKNOWN
Home-page: UNKNOWN
Author: Karol Polit
Author-email: 256438@student.pwr.edu.pl
License: UNKNOWN
Platform: UNKNOWN
Requires-Dist: requests
